apolo_events_client/__init__.py
apolo_events_client/_client.py
apolo_events_client/_config.py
apolo_events_client/_constants.py
apolo_events_client/_events.py
apolo_events_client/_exceptions.py
apolo_events_client/_messages.py
apolo_events_client/py.typed
apolo_events_client/pytest.py
apolo_events_client-25.10.0.dist-info/METADATA
apolo_events_client-25.10.0.dist-info/WHEEL
apolo_events_client-25.10.0.dist-info/entry_points.txt
apolo_events_client-25.10.0.dist-info/licenses/LICENSE
apolo_events_client-25.10.0.dist-info/RECORD
