Metadata-Version: 2.4
Name: apolo-events-client
Version: 25.10.0
Summary: Apolo client for platform-events
Author-email: Andrew Svetlov <andrew.svetlov@gmail.com>
License-File: LICENSE
Requires-Python: >=3.10
Requires-Dist: aiohttp[speedups]>=3.12.7
Requires-Dist: pydantic>=2.11.5
Provides-Extra: pytest
Requires-Dist: pytest-aiohttp>=1.1.0; extra == 'pytest'
Requires-Dist: pytest-asyncio>=1.0.0; extra == 'pytest'
Requires-Dist: pytest>=8.4.1; extra == 'pytest'
